get_json/__init__.py
get_json/tools/__init__.py
get_json/tools/get_json_tool.py
get_json/tools/utils.py
get_json/yamls/get_json_tool.yaml
tests/__init__.py
tests/test_get_json_tool.py
get_json_propmtflow_test_az-0.3.2.dist-info/METADATA
get_json_propmtflow_test_az-0.3.2.dist-info/WHEEL
get_json_propmtflow_test_az-0.3.2.dist-info/entry_points.txt
get_json_propmtflow_test_az-0.3.2.dist-info/top_level.txt
get_json_propmtflow_test_az-0.3.2.dist-info/RECORD
