Metadata-Version: 2.1
Name: get-json-propmtflow-test-az
Version: 0.3.2
Summary: This is my tools package
Home-page: UNKNOWN
Author: UNKNOWN
Author-email: UNKNOWN
License: UNKNOWN
Platform: UNKNOWN
